{
  "summary": {
    "total_blocks": 5
  },
  "blocks": {
    "0": {
      "line_num": [
        0,
        5
      ],
      "next": [
        "1",
        null
      ],
      "code": [
        "S = 0",
        "I = 1",
        "N = 100",
        "T_136 = I - 2",
        "J = T_136 * 2",
        "J = J - 1"
      ],
      "defd": [
        "I",
        "S",
        "N",
        "J",
        "T_136"
      ],
      "used": [],
      "in": [],
      "out": [
        "N",
        "J",
        "I",
        "S"
      ]
    },
    "1": {
      "line_num": [
        6,
        6
      ],
      "next": [
        "2",
        "3"
      ],
      "code": [
        "? I > N : 11"
      ],
      "defd": [],
      "used": [
        "N",
        "I"
      ],
      "in": [
        "N",
        "J",
        "I",
        "S"
      ],
      "out": [
        "I",
        "S",
        "N",
        "J"
      ]
    },
    "2": {
      "line_num": [
        7,
        10
      ],
      "next": [
        "3",
        null
      ],
      "code": [
        "T_182 = 2 * 2",
        "J = J + T_182",
        "S = S + J",
        "I = I + 2"
      ],
      "defd": [
        "T_182"
      ],
      "used": [
        "J",
        "I",
        "S"
      ],
      "in": [
        "N",
        "J",
        "I",
        "S"
      ],
      "out": [
        "N",
        "J",
        "I",
        "S"
      ]
    },
    "3": {
      "line_num": [
        11,
        11
      ],
      "next": [
        "1",
        null
      ],
      "code": [
        "!: 6"
      ],
      "defd": [],
      "used": [],
      "in": [
        "N",
        "J",
        "I",
        "S"
      ],
      "out": [
        "I",
        "S",
        "N",
        "J"
      ]
    },
    "4": {
      "line_num": [
        12,
        12
      ],
      "next": [
        null,
        null
      ],
      "code": [
        "HALT"
      ],
      "defd": [],
      "used": [],
      "in": [],
      "out": []
    }
  }
}