{
  "summary": {
    "total_blocks": 10
  },
  "blocks": {
    "0": {
      "line_num": [
        0,
        0
      ],
      "next": [
        "1",
        null
      ],
      "code": [
        "B0 = 0"
      ],
      "defd": [
        "B0"
      ],
      "used": [],
      "in": [
        "B2",
        "B4"
      ],
      "out": [
        "B0",
        "B4",
        "B2"
      ],
      "pre": [],
      "dom": [
        "0"
      ]
    },
    "1": {
      "line_num": [
        1,
        2
      ],
      "next": [
        "2",
        "6"
      ],
      "code": [
        "B1 = 1",
        "? B1 > B0 : 11"
      ],
      "defd": [
        "B1"
      ],
      "used": [
        "B0"
      ],
      "in": [
        "B0",
        "B2",
        "B4"
      ],
      "out": [
        "B0",
        "B4",
        "B2"
      ],
      "pre": [
        "4",
        "0"
      ],
      "dom": [
        "1",
        "0"
      ]
    },
    "2": {
      "line_num": [
        3,
        4
      ],
      "next": [
        "4",
        null
      ],
      "code": [
        "B2 = 2",
        "!: 7"
      ],
      "defd": [
        "B2"
      ],
      "used": [],
      "in": [
        "B0",
        "B4"
      ],
      "out": [
        "B0",
        "B4",
        "B2"
      ],
      "pre": [
        "1"
      ],
      "dom": [
        "1",
        "2",
        "0"
      ]
    },
    "3": {
      "line_num": [
        5,
        6
      ],
      "next": [
        "4",
        null
      ],
      "code": [
        "T0 = 233",
        "T1 = 233"
      ],
      "defd": [
        "T1",
        "T0"
      ],
      "used": [],
      "in": [
        "B0",
        "B2",
        "B4"
      ],
      "out": [
        "B0",
        "B4",
        "B2"
      ],
      "pre": [],
      "dom": []
    },
    "4": {
      "line_num": [
        7,
        8
      ],
      "next": [
        "5",
        "1"
      ],
      "code": [
        "B3 = 3",
        "? B3 > B2 : 1"
      ],
      "defd": [
        "B3"
      ],
      "used": [
        "B2"
      ],
      "in": [
        "B0",
        "B2",
        "B4"
      ],
      "out": [
        "B0",
        "B4",
        "B2"
      ],
      "pre": [
        "8",
        "3",
        "2"
      ],
      "dom": [
        "4",
        "1",
        "0"
      ]
    },
    "5": {
      "line_num": [
        9,
        10
      ],
      "next": [
        null,
        null
      ],
      "code": [
        "B4 = 4",
        "HALT"
      ],
      "defd": [
        "B4"
      ],
      "used": [],
      "in": [],
      "out": [],
      "pre": [
        "4"
      ],
      "dom": [
        "5",
        "4",
        "1",
        "0"
      ]
    },
    "6": {
      "line_num": [
        11,
        12
      ],
      "next": [
        "7",
        "9"
      ],
      "code": [
        "B5 = 5",
        "? B5 > B4 : 16"
      ],
      "defd": [
        "B5"
      ],
      "used": [
        "B4"
      ],
      "in": [
        "B0",
        "B2",
        "B4"
      ],
      "out": [
        "B0",
        "B4",
        "B2"
      ],
      "pre": [
        "1"
      ],
      "dom": [
        "6",
        "1",
        "0"
      ]
    },
    "7": {
      "line_num": [
        13,
        13
      ],
      "next": [
        "8",
        null
      ],
      "code": [
        "B6 = 6"
      ],
      "defd": [
        "B6"
      ],
      "used": [],
      "in": [
        "B0",
        "B2",
        "B4"
      ],
      "out": [
        "B0",
        "B4",
        "B2"
      ],
      "pre": [
        "6"
      ],
      "dom": [
        "6",
        "1",
        "0",
        "7"
      ]
    },
    "8": {
      "line_num": [
        14,
        15
      ],
      "next": [
        "4",
        null
      ],
      "code": [
        "B7 = 7",
        "!: 7"
      ],
      "defd": [
        "B7"
      ],
      "used": [],
      "in": [
        "B0",
        "B2",
        "B4"
      ],
      "out": [
        "B0",
        "B4",
        "B2"
      ],
      "pre": [
        "9",
        "7"
      ],
      "dom": [
        "8",
        "6",
        "1",
        "0"
      ]
    },
    "9": {
      "line_num": [
        16,
        17
      ],
      "next": [
        "8",
        null
      ],
      "code": [
        "B8 = 8",
        "!: 14"
      ],
      "defd": [
        "B8"
      ],
      "used": [],
      "in": [
        "B0",
        "B2",
        "B4"
      ],
      "out": [
        "B0",
        "B4",
        "B2"
      ],
      "pre": [
        "6"
      ],
      "dom": [
        "6",
        "9",
        "1",
        "0"
      ]
    }
  },
  "loops": [
    {
      "loop_blks": [
        "1",
        "2",
        "4",
        "6",
        "7",
        "8",
        "9"
      ],
      "back_edge": [
        "4",
        "1"
      ]
    }
  ]
}